topsis/__init__.py
topsis/topsis.py
Topsis_Manan_102203667-1.0.0.dist-info/METADATA
Topsis_Manan_102203667-1.0.0.dist-info/WHEEL
Topsis_Manan_102203667-1.0.0.dist-info/top_level.txt
Topsis_Manan_102203667-1.0.0.dist-info/RECORD
