Metadata-Version: 2.2
Name: Topsis-Manan-102203667
Version: 1.0.0
Summary: A Python package for TOPSIS analysis
Author: Manan Jindal
Author-email: manan@example.com
Classifier: Programming Language :: Python :: 3
Classifier: License :: OSI Approved :: MIT License
Classifier: Operating System :: OS Independent
Requires-Dist: numpy
Requires-Dist: pandas
Dynamic: author
Dynamic: author-email
Dynamic: classifier
Dynamic: requires-dist
Dynamic: summary
